magidict/__init__.py
magidict/__init__.pyi
magidict/_magidict.c
magidict/_magidict.cp313-win_amd64.pyd
magidict/_magidict.pyi
magidict/core.py
magidict/core.pyi
magidict-0.2.0.dist-info/licenses/LICENSE
magidict-0.2.0.dist-info/METADATA
magidict-0.2.0.dist-info/WHEEL
magidict-0.2.0.dist-info/top_level.txt
magidict-0.2.0.dist-info/RECORD
