Metadata-Version: 2.4
Name: magidict
Version: 0.2.0
Summary: A recursive dictionary with safe attribute access and automatic conversion.
Home-page: https://github.com/hristokbonev/magidict
Author: Hristo Bonev
Author-email: Hristo Bonev <chkbonev@gmail.com>
License-Expression: MIT
Project-URL: Homepage, https://github.com/hristokbonev/magidict
Project-URL: Issues, https://github.com/hristokbonev/magidict/issues
Keywords: dictionary,nested dict,magic dict,magidict,safe access,dot notation,attribute access,dotdict,recursive dict,json,data structure,python utility,mapping,dynamic object,flexible dict,auto convert,dict wrapper,smart dict,object-like dict,data helper,config parser,config manager,attribute dict,namespace dict,chainable access,python tools
Classifier: Programming Language :: Python :: 3
Classifier: Operating System :: OS Independent
Requires-Python: >=3.8
License-File: LICENSE
Dynamic: author
Dynamic: home-page
Dynamic: license-file
Dynamic: requires-python
